sce_minigame_publisher.py
sce_minigame_publisher-0.1.7.dist-info/METADATA
sce_minigame_publisher-0.1.7.dist-info/WHEEL
sce_minigame_publisher-0.1.7.dist-info/entry_points.txt
sce_minigame_publisher-0.1.7.dist-info/top_level.txt
sce_minigame_publisher-0.1.7.dist-info/RECORD
