Metadata-Version: 2.4
Name: sce-minigame-publisher
Version: 0.1.7
Summary: TapTap SCE小游戏自动发布工具
Author: SCE Team
Author-email: jl@xd.com
Classifier: Programming Language :: Python :: 3
Classifier: License :: OSI Approved :: MIT License
Classifier: Operating System :: OS Independent
Requires-Python: >=3.6
Requires-Dist: requests
Requires-Dist: python-dotenv
Dynamic: author
Dynamic: author-email
Dynamic: classifier
Dynamic: description
Dynamic: description-content-type
Dynamic: requires-dist
Dynamic: requires-python
Dynamic: summary
